xlwings_mcp/__main__.py
xlwings_mcp/exceptions.py
xlwings_mcp/force_close.py
xlwings_mcp/server.py
xlwings_mcp/session.py
xlwings_mcp/sheet.py
xlwings_mcp/workbook.py
xlwings_mcp/xlwings_impl/__init__.py
xlwings_mcp/xlwings_impl/advanced_xlw.py
xlwings_mcp/xlwings_impl/advanced_xlw_with_wb.py
xlwings_mcp/xlwings_impl/base.py
xlwings_mcp/xlwings_impl/calculations_xlw.py
xlwings_mcp/xlwings_impl/data_xlw.py
xlwings_mcp/xlwings_impl/formatting_xlw.py
xlwings_mcp/xlwings_impl/helpers.py
xlwings_mcp/xlwings_impl/range_xlw.py
xlwings_mcp/xlwings_impl/rows_cols_xlw.py
xlwings_mcp/xlwings_impl/sheet_xlw.py
xlwings_mcp/xlwings_impl/validation_xlw.py
xlwings_mcp/xlwings_impl/workbook_xlw.py
xlwings_mcp_server-1.0.1.dist-info/METADATA
xlwings_mcp_server-1.0.1.dist-info/WHEEL
xlwings_mcp_server-1.0.1.dist-info/entry_points.txt
xlwings_mcp_server-1.0.1.dist-info/licenses/LICENSE
xlwings_mcp_server-1.0.1.dist-info/RECORD
