Metadata-Version: 2.4
Name: xlwings-mcp-server
Version: 1.0.1
Summary: Excel MCP Server for manipulating Excel files using xlwings
Author-email: haris <haris.musa@outlook.com>
License-File: LICENSE
Requires-Python: >=3.10
Requires-Dist: fastmcp<3.0.0,>=2.0.0
Requires-Dist: mcp[cli]>=1.10.1
Requires-Dist: psutil>=5.9.0
Requires-Dist: pywin32>=306; sys_platform == 'win32'
Requires-Dist: typer>=0.16.0
Requires-Dist: xlwings>=0.30.0
